xia_meta_task/__init__.py
xia_meta_task/base.cpython-39-x86_64-linux-gnu.so
xia_meta_task/log.cpython-39-x86_64-linux-gnu.so
xia_meta_task/task.cpython-39-x86_64-linux-gnu.so
xia_meta_task-0.1.2.dist-info/LICENSE.txt
xia_meta_task-0.1.2.dist-info/METADATA
xia_meta_task-0.1.2.dist-info/WHEEL
xia_meta_task-0.1.2.dist-info/top_level.txt
xia_meta_task-0.1.2.dist-info/RECORD
