Metadata-Version: 2.1
Name: xia-meta-task
Version: 0.1.2
Summary: X-I-A Meta Task
Home-page: https://develop.x-i-a.com/docs/xia-meta-task/0.1.2/index.html
Author: X-I-A
Author-email: admin@x-i-a.com
License: UNKNOWN
Platform: UNKNOWN
Requires-Python: >=3.9
License-File: LICENSE.txt
Requires-Dist: flask
Requires-Dist: xia-engine-firestore
Requires-Dist: xia-meta
